LICENSE
MANIFEST.in
README.rst
setup.py
pyavagen/__init__.py
pyavagen/fields.py
pyavagen/generators.py
pyavagen/utils.py
pyavagen/validators.py
pyavagen/version.py
pyavagen.egg-info/PKG-INFO
pyavagen.egg-info/SOURCES.txt
pyavagen.egg-info/dependency_links.txt
pyavagen.egg-info/requires.txt
pyavagen.egg-info/top_level.txt
pyavagen/fonts/Comfortaa-Regular.ttf