Metadata-Version: 1.1
Name: pyavagen
Version: 0.2.1
Summary: Avatars generation of different types
Home-page: https://github.com/abalx/pyavagen
Author: Alexander Abrosimov
Author-email: to100100100@gmail.com
License: MIT
Keywords: image,avatar
Platform: UNKNOWN
Classifier: Development Status :: 4 - Beta
Classifier: Programming Language :: Python :: 3
Classifier: Programming Language :: Python :: 3.6
Classifier: Intended Audience :: Developers
Classifier: License :: OSI Approved :: MIT License
Classifier: Topic :: Multimedia :: Graphics
Requires: python (>= 3.6)
